{
  "papi_version":"7.1.0.0",
  "cpu_info":"Intel(R) Xeon(R) Gold 6126 CPU @ 2.60GHz",
  "max_cpu_rate_mhz":"3700",
  "min_cpu_rate_mhz":"1000",
  "event_definitions":{
    "rapl:::PACKAGE_ENERGY:PACKAGE0":{
      "component":"rapl",
      "type":"delta"
    },
    "rapl:::PACKAGE_ENERGY:PACKAGE1":{
      "component":"rapl",
      "type":"delta"
    },
    "rapl:::DRAM_ENERGY:PACKAGE0":{
      "component":"rapl",
      "type":"delta"
    },
    "rapl:::DRAM_ENERGY:PACKAGE1":{
      "component":"rapl",
      "type":"delta"
    },
    "PAPI_L1_DCM":{
      "component":"perf_event",
      "type":"delta"
    },
    "PAPI_L2_DCM":{
      "component":"perf_event",
      "type":"delta"
    },
    "PAPI_L2_DCR":{
      "component":"perf_event",
      "type":"delta"
    },
    "perf::TASK-CLOCK":{
      "component":"perf_event",
      "type":"delta"
    },
    "PAPI_TOT_INS":{
      "component":"perf_event",
      "type":"delta"
    },
    "nvml:::Tesla_V100-PCIE-32GB:device_0:power":{
      "component":"nvml",
      "type":"instant"
    },
    "nvml:::Tesla_V100-PCIE-32GB:device_0:gpu_utilization":{
      "component":"nvml",
      "type":"instant"
    },
    "nvml:::Tesla_V100-PCIE-32GB:device_0:memory_utilization":{
      "component":"nvml",
      "type":"instant"
    }
  },
  "threads":{
    "0":{
      "regions":{
        "0":{
          "name":"computation",
          "parent_region_id":"-1",
          "cycles":"3225787588",
          "real_time_nsec":"1243642599",
          "rapl:::PACKAGE_ENERGY:PACKAGE0":"75750366211",
          "rapl:::PACKAGE_ENERGY:PACKAGE1":"82333984375",
          "rapl:::DRAM_ENERGY:PACKAGE0":"6353424072",
          "rapl:::DRAM_ENERGY:PACKAGE1":"10014953613",
          "PAPI_L1_DCM":"3449384",
          "PAPI_L2_DCM":"1421588",
          "PAPI_L2_DCR":"2036449",
          "perf::TASK-CLOCK":"489928845",
          "PAPI_TOT_INS":"1038500301",
          "nvml:::Tesla_V100-PCIE-32GB:device_0:power":"36383",
          "nvml:::Tesla_V100-PCIE-32GB:device_0:gpu_utilization":"0",
          "nvml:::Tesla_V100-PCIE-32GB:device_0:memory_utilization":"0"
        },
        "1":{
          "name":"computation",
          "parent_region_id":"-1",
          "cycles":"420171454",
          "real_time_nsec":"161990069",
          "rapl:::PACKAGE_ENERGY:PACKAGE0":"16520263672",
          "rapl:::PACKAGE_ENERGY:PACKAGE1":"17640441894",
          "rapl:::DRAM_ENERGY:PACKAGE0":"1242492676",
          "rapl:::DRAM_ENERGY:PACKAGE1":"1340194703",
          "PAPI_L1_DCM":"813981",
          "PAPI_L2_DCM":"131788",
          "PAPI_L2_DCR":"529933",
          "perf::TASK-CLOCK":"159787996",
          "PAPI_TOT_INS":"845391109",
          "nvml:::Tesla_V100-PCIE-32GB:device_0:power":"36389",
          "nvml:::Tesla_V100-PCIE-32GB:device_0:gpu_utilization":"1",
          "nvml:::Tesla_V100-PCIE-32GB:device_0:memory_utilization":"0"
        },
        "2":{
          "name":"computation",
          "parent_region_id":"-1",
          "cycles":"425986228",
          "real_time_nsec":"164237160",
          "rapl:::PACKAGE_ENERGY:PACKAGE0":"17558410645",
          "rapl:::PACKAGE_ENERGY:PACKAGE1":"17906372070",
          "rapl:::DRAM_ENERGY:PACKAGE0":"1281173706",
          "rapl:::DRAM_ENERGY:PACKAGE1":"1372497559",
          "PAPI_L1_DCM":"866596",
          "PAPI_L2_DCM":"151442",
          "PAPI_L2_DCR":"574291",
          "perf::TASK-CLOCK":"164010222",
          "PAPI_TOT_INS":"844751439",
          "nvml:::Tesla_V100-PCIE-32GB:device_0:power":"36383",
          "nvml:::Tesla_V100-PCIE-32GB:device_0:gpu_utilization":"1",
          "nvml:::Tesla_V100-PCIE-32GB:device_0:memory_utilization":"0"
        },
        "3":{
          "name":"computation",
          "parent_region_id":"-1",
          "cycles":"419307888",
          "real_time_nsec":"161656850",
          "rapl:::PACKAGE_ENERGY:PACKAGE0":"17303833008",
          "rapl:::PACKAGE_ENERGY:PACKAGE1":"17434692383",
          "rapl:::DRAM_ENERGY:PACKAGE0":"1244247437",
          "rapl:::DRAM_ENERGY:PACKAGE1":"1340301514",
          "PAPI_L1_DCM":"904123",
          "PAPI_L2_DCM":"166788",
          "PAPI_L2_DCR":"603970",
          "perf::TASK-CLOCK":"159540617",
          "PAPI_TOT_INS":"845304421",
          "nvml:::Tesla_V100-PCIE-32GB:device_0:power":"36383",
          "nvml:::Tesla_V100-PCIE-32GB:device_0:gpu_utilization":"1",
          "nvml:::Tesla_V100-PCIE-32GB:device_0:memory_utilization":"0"
        },
        "4":{
          "name":"computation",
          "parent_region_id":"-1",
          "cycles":"417405146",
          "real_time_nsec":"160923831",
          "rapl:::PACKAGE_ENERGY:PACKAGE0":"17994689942",
          "rapl:::PACKAGE_ENERGY:PACKAGE1":"17092529297",
          "rapl:::DRAM_ENERGY:PACKAGE0":"1248855591",
          "rapl:::DRAM_ENERGY:PACKAGE1":"1346878052",
          "PAPI_L1_DCM":"946192",
          "PAPI_L2_DCM":"189310",
          "PAPI_L2_DCR":"637861",
          "perf::TASK-CLOCK":"160814337",
          "PAPI_TOT_INS":"845102142",
          "nvml:::Tesla_V100-PCIE-32GB:device_0:power":"36383",
          "nvml:::Tesla_V100-PCIE-32GB:device_0:gpu_utilization":"1",
          "nvml:::Tesla_V100-PCIE-32GB:device_0:memory_utilization":"0"
        },
        "5":{
          "name":"computation",
          "parent_region_id":"-1",
          "cycles":"414937988",
          "real_time_nsec":"159971936",
          "rapl:::PACKAGE_ENERGY:PACKAGE0":"17784057617",
          "rapl:::PACKAGE_ENERGY:PACKAGE1":"16712036133",
          "rapl:::DRAM_ENERGY:PACKAGE0":"1223724365",
          "rapl:::DRAM_ENERGY:PACKAGE1":"1321929932",
          "PAPI_L1_DCM":"992082",
          "PAPI_L2_DCM":"214807",
          "PAPI_L2_DCR":"678692",
          "perf::TASK-CLOCK":"157819354",
          "PAPI_TOT_INS":"845651077",
          "nvml:::Tesla_V100-PCIE-32GB:device_0:power":"36383",
          "nvml:::Tesla_V100-PCIE-32GB:device_0:gpu_utilization":"1",
          "nvml:::Tesla_V100-PCIE-32GB:device_0:memory_utilization":"0"
        },
        "6":{
          "name":"computation",
          "parent_region_id":"-1",
          "cycles":"415607556",
          "real_time_nsec":"160229856",
          "rapl:::PACKAGE_ENERGY:PACKAGE0":"18019653321",
          "rapl:::PACKAGE_ENERGY:PACKAGE1":"17033813477",
          "rapl:::DRAM_ENERGY:PACKAGE0":"1240249634",
          "rapl:::DRAM_ENERGY:PACKAGE1":"1348114014",
          "PAPI_L1_DCM":"1036680",
          "PAPI_L2_DCM":"236273",
          "PAPI_L2_DCR":"715781",
          "perf::TASK-CLOCK":"160079817",
          "PAPI_TOT_INS":"846151201",
          "nvml:::Tesla_V100-PCIE-32GB:device_0:power":"36383",
          "nvml:::Tesla_V100-PCIE-32GB:device_0:gpu_utilization":"1",
          "nvml:::Tesla_V100-PCIE-32GB:device_0:memory_utilization":"0"
        },
        "7":{
          "name":"computation",
          "parent_region_id":"-1",
          "cycles":"426082010",
          "real_time_nsec":"164268481",
          "rapl:::PACKAGE_ENERGY:PACKAGE0":"18465942383",
          "rapl:::PACKAGE_ENERGY:PACKAGE1":"17372741699",
          "rapl:::DRAM_ENERGY:PACKAGE0":"1277465821",
          "rapl:::DRAM_ENERGY:PACKAGE1":"1380340576",
          "PAPI_L1_DCM":"1320103",
          "PAPI_L2_DCM":"459747",
          "PAPI_L2_DCR":"949474",
          "perf::TASK-CLOCK":"163542140",
          "PAPI_TOT_INS":"851728171",
          "nvml:::Tesla_V100-PCIE-32GB:device_0:power":"36577",
          "nvml:::Tesla_V100-PCIE-32GB:device_0:gpu_utilization":"1",
          "nvml:::Tesla_V100-PCIE-32GB:device_0:memory_utilization":"0"
        },
        "8":{
          "name":"computation",
          "parent_region_id":"-1",
          "cycles":"432233912",
          "real_time_nsec":"166640032",
          "rapl:::PACKAGE_ENERGY:PACKAGE0":"18824340821",
          "rapl:::PACKAGE_ENERGY:PACKAGE1":"17720214843",
          "rapl:::DRAM_ENERGY:PACKAGE0":"1305923462",
          "rapl:::DRAM_ENERGY:PACKAGE1":"1409820556",
          "PAPI_L1_DCM":"1829425",
          "PAPI_L2_DCM":"794171",
          "PAPI_L2_DCR":"1376330",
          "perf::TASK-CLOCK":"166625037",
          "PAPI_TOT_INS":"863765117",
          "nvml:::Tesla_V100-PCIE-32GB:device_0:power":"37258",
          "nvml:::Tesla_V100-PCIE-32GB:device_0:gpu_utilization":"3",
          "nvml:::Tesla_V100-PCIE-32GB:device_0:memory_utilization":"0"
        },
        "9":{
          "name":"computation",
          "parent_region_id":"-1",
          "cycles":"458591490",
          "real_time_nsec":"176801613",
          "rapl:::PACKAGE_ENERGY:PACKAGE0":"19532165527",
          "rapl:::PACKAGE_ENERGY:PACKAGE1":"18812805176",
          "rapl:::DRAM_ENERGY:PACKAGE0":"1388015747",
          "rapl:::DRAM_ENERGY:PACKAGE1":"1477493286",
          "PAPI_L1_DCM":"2483173",
          "PAPI_L2_DCM":"1280486",
          "PAPI_L2_DCR":"1904109",
          "perf::TASK-CLOCK":"176729228",
          "PAPI_TOT_INS":"877930208",
          "nvml:::Tesla_V100-PCIE-32GB:device_0:power":"38523",
          "nvml:::Tesla_V100-PCIE-32GB:device_0:gpu_utilization":"4",
          "nvml:::Tesla_V100-PCIE-32GB:device_0:memory_utilization":"0"
        },
        "10":{
          "name":"computation",
          "parent_region_id":"-1",
          "cycles":"484967606",
          "real_time_nsec":"186970820",
          "rapl:::PACKAGE_ENERGY:PACKAGE0":"20775573730",
          "rapl:::PACKAGE_ENERGY:PACKAGE1":"19992919922",
          "rapl:::DRAM_ENERGY:PACKAGE0":"1462539673",
          "rapl:::DRAM_ENERGY:PACKAGE1":"1595779419",
          "PAPI_L1_DCM":"3340642",
          "PAPI_L2_DCM":"1868697",
          "PAPI_L2_DCR":"2625098",
          "perf::TASK-CLOCK":"186825565",
          "PAPI_TOT_INS":"896264242",
          "nvml:::Tesla_V100-PCIE-32GB:device_0:power":"39001",
          "nvml:::Tesla_V100-PCIE-32GB:device_0:gpu_utilization":"9",
          "nvml:::Tesla_V100-PCIE-32GB:device_0:memory_utilization":"0"
        },
        "11":{
          "name":"computation",
          "parent_region_id":"-1",
          "cycles":"508978674",
          "real_time_nsec":"196227545",
          "rapl:::PACKAGE_ENERGY:PACKAGE0":"21773315429",
          "rapl:::PACKAGE_ENERGY:PACKAGE1":"20984802246",
          "rapl:::DRAM_ENERGY:PACKAGE0":"1546081543",
          "rapl:::DRAM_ENERGY:PACKAGE1":"1659027100",
          "PAPI_L1_DCM":"4423207",
          "PAPI_L2_DCM":"2591519",
          "PAPI_L2_DCR":"3531012",
          "perf::TASK-CLOCK":"196144556",
          "PAPI_TOT_INS":"920174134",
          "nvml:::Tesla_V100-PCIE-32GB:device_0:power":"41130",
          "nvml:::Tesla_V100-PCIE-32GB:device_0:gpu_utilization":"10",
          "nvml:::Tesla_V100-PCIE-32GB:device_0:memory_utilization":"0"
        },
        "12":{
          "name":"computation",
          "parent_region_id":"-1",
          "cycles":"562492690",
          "real_time_nsec":"216859350",
          "rapl:::PACKAGE_ENERGY:PACKAGE0":"23875244141",
          "rapl:::PACKAGE_ENERGY:PACKAGE1":"22991516113",
          "rapl:::DRAM_ENERGY:PACKAGE0":"1713500977",
          "rapl:::DRAM_ENERGY:PACKAGE1":"1870407105",
          "PAPI_L1_DCM":"5687984",
          "PAPI_L2_DCM":"3429640",
          "PAPI_L2_DCR":"4591481",
          "perf::TASK-CLOCK":"214291137",
          "PAPI_TOT_INS":"951845370",
          "nvml:::Tesla_V100-PCIE-32GB:device_0:power":"42191",
          "nvml:::Tesla_V100-PCIE-32GB:device_0:gpu_utilization":"11",
          "nvml:::Tesla_V100-PCIE-32GB:device_0:memory_utilization":"0"
        },
        "13":{
          "name":"computation",
          "parent_region_id":"-1",
          "cycles":"597757604",
          "real_time_nsec":"230435902",
          "rapl:::PACKAGE_ENERGY:PACKAGE0":"25686218261",
          "rapl:::PACKAGE_ENERGY:PACKAGE1":"24792175293",
          "rapl:::DRAM_ENERGY:PACKAGE0":"1851531982",
          "rapl:::DRAM_ENERGY:PACKAGE1":"2010498046",
          "PAPI_L1_DCM":"7267934",
          "PAPI_L2_DCM":"4391762",
          "PAPI_L2_DCR":"5814942",
          "perf::TASK-CLOCK":"230499083",
          "PAPI_TOT_INS":"989195472",
          "nvml:::Tesla_V100-PCIE-32GB:device_0:power":"46177",
          "nvml:::Tesla_V100-PCIE-32GB:device_0:gpu_utilization":"16",
          "nvml:::Tesla_V100-PCIE-32GB:device_0:memory_utilization":"1"
        },
        "14":{
          "name":"computation",
          "parent_region_id":"-1",
          "cycles":"1201800858",
          "real_time_nsec":"463332849",
          "rapl:::PACKAGE_ENERGY:PACKAGE0":"52116271972",
          "rapl:::PACKAGE_ENERGY:PACKAGE1":"50524108886",
          "rapl:::DRAM_ENERGY:PACKAGE0":"3861404419",
          "rapl:::DRAM_ENERGY:PACKAGE1":"4285766602",
          "PAPI_L1_DCM":"32023297",
          "PAPI_L2_DCM":"16547669",
          "PAPI_L2_DCR":"23063325",
          "perf::TASK-CLOCK":"463217263",
          "PAPI_TOT_INS":"1682423561",
          "nvml:::Tesla_V100-PCIE-32GB:device_0:power":"94118",
          "nvml:::Tesla_V100-PCIE-32GB:device_0:gpu_utilization":"54",
          "nvml:::Tesla_V100-PCIE-32GB:device_0:memory_utilization":"16"
        },
        "15":{
          "name":"computation",
          "parent_region_id":"-1",
          "cycles":"2470378614",
          "real_time_nsec":"952403616",
          "rapl:::PACKAGE_ENERGY:PACKAGE0":"107082031250",
          "rapl:::PACKAGE_ENERGY:PACKAGE1":"104248413086",
          "rapl:::DRAM_ENERGY:PACKAGE0":"7846908569",
          "rapl:::DRAM_ENERGY:PACKAGE1":"8975738525",
          "PAPI_L1_DCM":"83307317",
          "PAPI_L2_DCM":"36743309",
          "PAPI_L2_DCR":"61785708",
          "perf::TASK-CLOCK":"945718335",
          "PAPI_TOT_INS":"3348850843",
          "nvml:::Tesla_V100-PCIE-32GB:device_0:power":"100940",
          "nvml:::Tesla_V100-PCIE-32GB:device_0:gpu_utilization":"73",
          "nvml:::Tesla_V100-PCIE-32GB:device_0:memory_utilization":"22"
        },
        "16":{
          "name":"computation",
          "parent_region_id":"-1",
          "cycles":"4603770488",
          "real_time_nsec":"1774897705",
          "rapl:::PACKAGE_ENERGY:PACKAGE0":"202019165039",
          "rapl:::PACKAGE_ENERGY:PACKAGE1":"195342224121",
          "rapl:::DRAM_ENERGY:PACKAGE0":"14666946411",
          "rapl:::DRAM_ENERGY:PACKAGE1":"16702499390",
          "PAPI_L1_DCM":"172298651",
          "PAPI_L2_DCM":"65048074",
          "PAPI_L2_DCR":"128897544",
          "perf::TASK-CLOCK":"1774420847",
          "PAPI_TOT_INS":"6305489255",
          "nvml:::Tesla_V100-PCIE-32GB:device_0:power":"98734",
          "nvml:::Tesla_V100-PCIE-32GB:device_0:gpu_utilization":"83",
          "nvml:::Tesla_V100-PCIE-32GB:device_0:memory_utilization":"32"
        },
        "17":{
          "name":"computation",
          "parent_region_id":"-1",
          "cycles":"8235040114",
          "real_time_nsec":"3174870165",
          "rapl:::PACKAGE_ENERGY:PACKAGE0":"362503356934",
          "rapl:::PACKAGE_ENERGY:PACKAGE1":"349890808105",
          "rapl:::DRAM_ENERGY:PACKAGE0":"25945602417",
          "rapl:::DRAM_ENERGY:PACKAGE1":"29486785889",
          "PAPI_L1_DCM":"371878235",
          "PAPI_L2_DCM":"101386800",
          "PAPI_L2_DCR":"269889187",
          "perf::TASK-CLOCK":"3170276073",
          "PAPI_TOT_INS":"13265121760",
          "nvml:::Tesla_V100-PCIE-32GB:device_0:power":"79675",
          "nvml:::Tesla_V100-PCIE-32GB:device_0:gpu_utilization":"88",
          "nvml:::Tesla_V100-PCIE-32GB:device_0:memory_utilization":"32"
        },
        "18":{
          "name":"computation",
          "parent_region_id":"-1",
          "cycles":"13131191864",
          "real_time_nsec":"5062038848",
          "rapl:::PACKAGE_ENERGY:PACKAGE0":"523364624023",
          "rapl:::PACKAGE_ENERGY:PACKAGE1":"492910888672",
          "rapl:::DRAM_ENERGY:PACKAGE0":"41406036377",
          "rapl:::DRAM_ENERGY:PACKAGE1":"43601470948",
          "PAPI_L1_DCM":"677700383",
          "PAPI_L2_DCM":"145548960",
          "PAPI_L2_DCR":"486679770",
          "perf::TASK-CLOCK":"5058419617",
          "PAPI_TOT_INS":"25234681234",
          "nvml:::Tesla_V100-PCIE-32GB:device_0:power":"68407",
          "nvml:::Tesla_V100-PCIE-32GB:device_0:gpu_utilization":"91",
          "nvml:::Tesla_V100-PCIE-32GB:device_0:memory_utilization":"34"
        },
        "19":{
          "name":"computation",
          "parent_region_id":"-1",
          "cycles":"19996905134",
          "real_time_nsec":"7709460890",
          "rapl:::PACKAGE_ENERGY:PACKAGE0":"681728515625",
          "rapl:::PACKAGE_ENERGY:PACKAGE1":"614648742676",
          "rapl:::DRAM_ENERGY:PACKAGE0":"62575851440",
          "rapl:::DRAM_ENERGY:PACKAGE1":"57661056518",
          "PAPI_L1_DCM":"1186630316",
          "PAPI_L2_DCM":"197948283",
          "PAPI_L2_DCR":"819456138",
          "perf::TASK-CLOCK":"7709009585",
          "PAPI_TOT_INS":"47101978409",
          "nvml:::Tesla_V100-PCIE-32GB:device_0:power":"59604",
          "nvml:::Tesla_V100-PCIE-32GB:device_0:gpu_utilization":"100",
          "nvml:::Tesla_V100-PCIE-32GB:device_0:memory_utilization":"50"
        },
        "20":{
          "name":"computation",
          "parent_region_id":"-1",
          "cycles":"28694759562",
          "real_time_nsec":"11062778894",
          "rapl:::PACKAGE_ENERGY:PACKAGE0":"882603698731",
          "rapl:::PACKAGE_ENERGY:PACKAGE1":"769657836914",
          "rapl:::DRAM_ENERGY:PACKAGE0":"89697753906",
          "rapl:::DRAM_ENERGY:PACKAGE1":"75731597901",
          "PAPI_L1_DCM":"1823995656",
          "PAPI_L2_DCM":"258758911",
          "PAPI_L2_DCR":"1245422805",
          "perf::TASK-CLOCK":"11062054505",
          "PAPI_TOT_INS":"75167137342",
          "nvml:::Tesla_V100-PCIE-32GB:device_0:power":"52736",
          "nvml:::Tesla_V100-PCIE-32GB:device_0:gpu_utilization":"100",
          "nvml:::Tesla_V100-PCIE-32GB:device_0:memory_utilization":"47"
        }
      }
    }
  }
}

