{
   "avx2" : {
      "1024" : {
         "error" : 0.0,
         "time" : 11.150893819999999
      },
      "112" : {
         "error" : 0.0,
         "time" : 0.10075276000000001
      },
      "128" : {
         "error" : 0.0,
         "time" : 0.10108561999999997
      },
      "256" : {
         "error" : 0.0,
         "time" : 0.18766663999999997
      },
      "32" : {
         "error" : 0.0,
         "time" : 0.12361318
      },
      "384" : {
         "error" : 0.0,
         "time" : 0.22382611999999996
      },
      "48" : {
         "error" : 0.0,
         "time" : 0.087890760000000012
      },
      "512" : {
         "error" : 0.0,
         "time" : 0.80541365999999981
      },
      "64" : {
         "error" : 0.0,
         "time" : 0.09902055999999998
      },
      "640" : {
         "error" : 0.0,
         "time" : 1.4872604400000002
      },
      "768" : {
         "error" : 0.0,
         "time" : 2.87970076
      },
      "80" : {
         "error" : 0.0,
         "time" : 0.095757119999999973
      },
      "896" : {
         "error" : 0.0,
         "time" : 5.9601331799999988
      },
      "96" : {
         "error" : 0.0,
         "time" : 0.097419499999999992
      },
      "2048" : {
         "error" : 0.0,
         "time" : 116.77791746
      },
      "3072" : {
         "error" : 0.0,
         "time" : 855.4028949599998
      },
      "4096" : {
         "error" : 0.0,
         "time" : 3339.2074834400009
      },
      "5120" : {
         "error" : 0.0,
         "time" : 5969.9770803000019
      },
      "6144" : {
         "error" : 0.0,
         "time" : 12070.756116159999
      },
      "7168" : {
         "error" : 0.0,
         "time" : 16792.921912419995
      },
      "8192" : {
         "error" : 0.0,
         "time" : 31510.090027640003
      }
   },
   "avx512" : {
      "1024" : {
         "error" : 0.0,
         "time" : 5.5148807199999998
      },
      "112" : {
         "error" : 0.0,
         "time" : 0.098091140000000049
      },
      "128" : {
         "error" : 0.0,
         "time" : 0.093431539999999966
      },
      "256" : {
         "error" : 0.0,
         "time" : 0.14466925999999999
      },
      "32" : {
         "error" : 0.0,
         "time" : 0.10054530000000002
      },
      "384" : {
         "error" : 0.0,
         "time" : 0.13092980000000001
      },
      "48" : {
         "error" : 0.0,
         "time" : 0.095568059999999982
      },
      "512" : {
         "error" : 0.0,
         "time" : 0.44489556000000008
      },
      "64" : {
         "error" : 0.0,
         "time" : 0.097675719999999994
      },
      "640" : {
         "error" : 0.0,
         "time" : 0.98974602000000023
      },
      "768" : {
         "error" : 0.0,
         "time" : 1.7168818400000001
      },
      "80" : {
         "error" : 0.0,
         "time" : 0.094203060000000019
      },
      "896" : {
         "error" : 0.0,
         "time" : 3.6170153400000009
      },
      "96" : {
         "error" : 0.0,
         "time" : 0.096869200000000003
      },
      "2048" : {
         "error" : 0.0,
         "time" : 50.343835040000002
      },
      "3072" : {
         "error" : 0.0,
         "time" : 677.81250383999998
      },
      "4096" : {
         "error" : 0.0,
         "time" : 1605.8353149000002
      },
      "5120" : {
         "error" : 0.0,
         "time" : 3791.3312336799991
      },
      "6144" : {
         "error" : 0.0,
         "time" : 6305.5610137600015
      },
      "7168" : {
         "error" : 0.0,
         "time" : 8967.9747561000004
      },
      "8192" : {
         "error" : 0.0,
         "time" : 15313.052412620002
      }
   },
   "mkl" : {
      "1024" : {
         "error" : 1.3250060604264036e-08,
         "time" : 1.6923336200000003
      },
      "112" : {
         "error" : 0.0,
         "time" : 0.1006475
      },
      "128" : {
         "error" : 0.0,
         "time" : 0.09255335999999996
      },
      "256" : {
         "error" : 0.0,
         "time" : 0.26868991999999992
      },
      "32" : {
         "error" : 0.0,
         "time" : 0.42226061999999981
      },
      "384" : {
         "error" : 0.0,
         "time" : 0.11828385999999999
      },
      "48" : {
         "error" : 0.0,
         "time" : 0.0034589199999999999
      },
      "512" : {
         "error" : 1.722026299333379e-09,
         "time" : 0.63242374000000023
      },
      "64" : {
         "error" : 0.0,
         "time" : 0.068454279999999978
      },
      "640" : {
         "error" : 4.40681979796409e-09,
         "time" : 0.41368873999999994
      },
      "768" : {
         "error" : 7.1997496853271059e-09,
         "time" : 1.20538656
      },
      "80" : {
         "error" : 0.0,
         "time" : 0.095105979999999979
      },
      "896" : {
         "error" : 9.7018340028398597e-09,
         "time" : 1.1898381399999998
      },
      "96" : {
         "error" : 0.0,
         "time" : 0.089077799999999985
      },
      "2048" : {
         "error" : 9.9827403232666256e-08,
         "time" : 12.150184860000001
      },
      "3072" : {
         "error" : 4.2319251747358066e-07,
         "time" : 44.967778459999991
      },
      "4096" : {
         "error" : 7.5165377211305895e-07,
         "time" : 89.735682119999979
      },
      "5120" : {
         "error" : 1.9115559553029016e-06,
         "time" : 153.84644040000001
      },
      "6144" : {
         "error" : 3.0200149012671318e-06,
         "time" : 269.53459525999995
      },
      "7168" : {
         "error" : 3.9716128412692342e-06,
         "time" : 323.69437559999994
      },
      "8192" : {
         "error" : 4.8166939450311475e-06,
         "time" : 441.69702989999996
      }
   },
   "openMP" : {
      "1024" : {
         "error" : 0.0,
         "time" : 4.03266378
      },
      "112" : {
         "error" : 0.0,
         "time" : 0.12287966000000003
      },
      "128" : {
         "error" : 0.0,
         "time" : 0.11736372000000003
      },
      "256" : {
         "error" : 0.0,
         "time" : 0.17960757999999999
      },
      "32" : {
         "error" : 0.0,
         "time" : 0.14158376000000003
      },
      "384" : {
         "error" : 0.0,
         "time" : 0.14411675999999995
      },
      "48" : {
         "error" : 0.0,
         "time" : 0.081716079999999969
      },
      "512" : {
         "error" : 0.0,
         "time" : 0.43649314
      },
      "64" : {
         "error" : 0.0,
         "time" : 0.10635840000000003
      },
      "640" : {
         "error" : 0.0,
         "time" : 0.99105559999999981
      },
      "768" : {
         "error" : 0.0,
         "time" : 1.6812292799999995
      },
      "80" : {
         "error" : 0.0,
         "time" : 0.11044556000000003
      },
      "896" : {
         "error" : 0.0,
         "time" : 2.7282259399999997
      },
      "96" : {
         "error" : 0.0,
         "time" : 0.11875425999999997
      },
      "2048" : {
         "error" : 0.0,
         "time" : 37.10771204000001
      },
      "3072" : {
         "error" : 0.0,
         "time" : 341.91745806
      },
      "4096" : {
         "error" : 0.0,
         "time" : 926.93059002000007
      },
      "5120" : {
         "error" : 0.0,
         "time" : 1721.6125642400002
      },
      "6144" : {
         "error" : 0.0,
         "time" : 3414.1892545399992
      },
      "7168" : {
         "error" : 0.0,
         "time" : 5139.7881408600006
      },
      "8192" : {
         "error" : 0.0,
         "time" : 8301.9319454600009
      }
   },
   "serial" : {
      "1024" : {
         "error" : 0.0,
         "time" : 189.71077022000003
      },
      "112" : {
         "error" : 0.0,
         "time" : 0.14784840000000002
      },
      "128" : {
         "error" : 0.0,
         "time" : 0.21495958000000001
      },
      "256" : {
         "error" : 0.0,
         "time" : 1.4285515800000004
      },
      "32" : {
         "error" : 0.0,
         "time" : 0.0061388999999999984
      },
      "384" : {
         "error" : 0.0,
         "time" : 4.7239036999999993
      },
      "48" : {
         "error" : 0.0,
         "time" : 0.015176580000000002
      },
      "512" : {
         "error" : 0.0,
         "time" : 15.577815300000005
      },
      "64" : {
         "error" : 0.0,
         "time" : 0.028045540000000001
      },
      "640" : {
         "error" : 0.0,
         "time" : 42.915223579999996
      },
      "768" : {
         "error" : 0.0,
         "time" : 80.740603760000013
      },
      "80" : {
         "error" : 0.0,
         "time" : 0.060058799999999996
      },
      "896" : {
         "error" : 0.0,
         "time" : 128.39784002000002
      },
      "96" : {
         "error" : 0.0,
         "time" : 0.097702419999999957
      },
      "2048" : {
         "error" : 0.0,
         "time" : 1331.7877403
      },
      "3072" : {
         "error" : 0.0,
         "time" : 6725.2948524399999
      },
      "4096" : {
         "error" : 0.0,
         "time" : 18783.451296240004
      },
      "5120" : {
         "error" : 0.0,
         "time" : 39321.943213899991
      },
      "6144" : {
         "error" : 0.0,
         "time" : 72577.029572459986
      },
      "7168" : {
         "error" : 0.0,
         "time" : 115335.86182792
      },
      "8192" : {
         "error" : 0.0,
         "time" : 175393.59885727998
      }
   }
}
